cli.py
callisto/__init__.py
callisto/app.py
callisto/built/index.html
callisto/built/static/callisto-256.png
callisto/built/static/favicon.png
callisto/built/static/css/app.5e43c96a.css
callisto/built/static/css/chunk-vendors.649be42d.css
callisto/built/static/js/app.3614770a.js
callisto/built/static/js/app.3614770a.js.map
callisto/built/static/js/chunk-vendors.1aef33bc.js
callisto/built/static/js/chunk-vendors.1aef33bc.js.map
callisto/contents_managers/__init__.py
callisto/contents_managers/s3.py
callisto/core/__init__.py
callisto/core/callisto_config.py
callisto/core/contents_loader.py
callisto/core/notebook_content.py
callisto/core/private_loader.py
callisto/core/toc.py
tests/__init__.py
tests/unit_tests/__init__.py
tests/unit_tests/conftest.py
tests/unit_tests/test_app.py
tests/unit_tests/contents_managers/__init__.py
tests/unit_tests/contents_managers/test_s3.py
tests/unit_tests/core/__init__.py
tests/unit_tests/core/test_callisto_config.py
tests/unit_tests/core/test_contents_loader.py
tests/unit_tests/core/test_notebook_content.py
tests/utils/__init__.py
tests/utils/create_s3.py
callisto_nbviewer-1.0.2.dist-info/LICENSE
callisto_nbviewer-1.0.2.dist-info/METADATA
callisto_nbviewer-1.0.2.dist-info/WHEEL
callisto_nbviewer-1.0.2.dist-info/entry_points.txt
callisto_nbviewer-1.0.2.dist-info/top_level.txt
callisto_nbviewer-1.0.2.dist-info/RECORD
