Metadata-Version: 2.1
Name: callisto-nbviewer
Version: 1.0.2
Summary: Jupyter notebook viewer
Home-page: https://github.com/lydian/callisto
Author: Lydian Lee
Author-email: lydianly@gmail.com
License: UNKNOWN
Platform: UNKNOWN
Classifier: Development Status :: 5 - Production/Stable
Classifier: Environment :: Web Environment
Classifier: Framework :: Flask
Classifier: Framework :: Jupyter
Classifier: License :: OSI Approved :: Apache Software License
Classifier: Natural Language :: English
Classifier: Operating System :: OS Independent
Classifier: Programming Language :: Python
License-File: LICENSE
Requires-Dist: boto3
Requires-Dist: bs4
Requires-Dist: click
Requires-Dist: cryptography
Requires-Dist: cssutils
Requires-Dist: flask
Requires-Dist: gunicorn
Requires-Dist: jinja2
Requires-Dist: jupyter-server
Requires-Dist: more-click
Requires-Dist: nbconvert
